CHANGES.rst
CONTRIBUTING.rst
LICENSE
README.rst
pyruvate-1.6.0.dist-info/METADATA
pyruvate-1.6.0.dist-info/WHEEL
pyruvate-1.6.0.dist-info/entry_points.txt
pyruvate-1.6.0.dist-info/licenses/LICENSE
pyruvate/__init__.py
pyruvate/_pyruvate.cpython-312-x86_64-linux-gnu.so
pyruvate-1.6.0.dist-info/RECORD
