Metadata-Version: 2.4
Name: pyruvate
Version: 1.6.0
Classifier: Development Status :: 5 - Production/Stable
Classifier: Environment :: Web Environment
Classifier: Intended Audience :: Developers
Classifier: Operating System :: POSIX :: Linux
Classifier: Operating System :: MacOS
Classifier: Programming Language :: Rust
Classifier: Programming Language :: Python :: Implementation :: CPython
Classifier: Programming Language :: Python :: 3
Classifier: Programming Language :: Python :: 3.10
Classifier: Programming Language :: Python :: 3.11
Classifier: Programming Language :: Python :: 3.12
Classifier: Programming Language :: Python :: 3.13
Classifier: Programming Language :: Python :: 3.14
Classifier: Topic :: Software Development :: Libraries :: Python Modules
Classifier: Topic :: Internet :: WWW/HTTP
Classifier: Topic :: Internet :: WWW/HTTP :: WSGI
Classifier: Topic :: Internet :: WWW/HTTP :: WSGI :: Server
Requires-Dist: aiohttp ; extra == 'test'
Requires-Dist: pytest ; extra == 'test'
Requires-Dist: pytest-asyncio ; extra == 'test'
Requires-Dist: requests ; extra == 'test'
Provides-Extra: test
License-File: LICENSE
Summary: WSGI server implemented in Rust.
Keywords: WSGI
Author: tschorr <t_schorr@gmx.de>
Author-email: Thomas Schorr <t_schorr@gmx.de>
Requires-Python: >=3.10
Project-URL: Repository, https://gitlab.com/tschorr/pyruvate
Project-URL: Issues, https://gitlab.com/tschorr/pyruvate/-/issues
Project-URL: Changelog, https://gitlab.com/tschorr/pyruvate/-/blob/main/CHANGES.rst?ref_type=heads
